totra/__init__.py
totra/core.py
totra/exceptions.py
totra/main.py
totra/output_format.py
totra/version.py
totra-0.1.3.data/data/README.md
totra-0.1.3.dist-info/LICENSE.txt
totra-0.1.3.dist-info/METADATA
totra-0.1.3.dist-info/RECORD
totra-0.1.3.dist-info/WHEEL
totra-0.1.3.dist-info/entry_points.txt
totra-0.1.3.dist-info/top_level.txt
