Metadata-Version: 2.1
Name: totra
Version: 0.1.3
Summary: Unofficial TopTracker CLI helper. TopTracker is at https://www.toptal.com/tracker
Home-page: https://github.com/jedrus2000/totra
Author: Andrzej Bargański
Author-email: a.barganski@gmail.com
License: MIT
Project-URL: Source, https://github.com/jedrus2000/totra/
Keywords: toptracker cli
Platform: UNKNOWN
Classifier: Development Status :: 1 - Planning
Classifier: Intended Audience :: End Users/Desktop
Classifier: Topic :: Utilities
Classifier: License :: OSI Approved :: MIT License
Classifier: Programming Language :: Python :: 3.6
Requires-Python: >=3.6
Provides-Extra: dev
Requires-Dist: requests
Requires-Dist: maya
Requires-Dist: openpyxl
Requires-Dist: docopt
Provides-Extra: dev
Requires-Dist: twine; extra == 'dev'
Requires-Dist: wheel; extra == 'dev'
